ndvi_trends/__init__.py
ndvi_trends/calc.py
ndvi_trends/data.py
ndvi_trends/smoothing.py
ndvi_trends/utils/__init__.py
ndvi_trends/utils/ee.py
ndvi_trends/utils/npxr.py
ndvi_trends-0.0.8.dist-info/LICENSE.md
ndvi_trends-0.0.8.dist-info/METADATA
ndvi_trends-0.0.8.dist-info/WHEEL
ndvi_trends-0.0.8.dist-info/top_level.txt
ndvi_trends-0.0.8.dist-info/RECORD
