Metadata-Version: 2.1
Name: ndvi_trends
Version: 0.0.8
License-File: LICENSE.md
